{
  "title":"Lecture 25: Homogeneous Linear Systems with Constant Coefficients",
  "description": "",
  "file": null,
  "learning_resource_types": ["Lecture Videos"],
  "resource_type": "Video",
  "file_type": null,
  "youtube_key":  "heBvViSi9xQ",
  "captions_file": "/courses/18-03-differential-equations-spring-2010/b139060a05d2593f97907b146a6d3405_heBvViSi9xQ.vtt",
  "transcript_file": "/courses/18-03-differential-equations-spring-2010/b10eb531875b86f1e6d45c165120a3f7_heBvViSi9xQ.pdf",
  "thumbnail_file": "https://img.youtube.com/vi/heBvViSi9xQ/default.jpg",
  "archive_url": "http://www.archive.org/download/MIT18.03S06/mit-ocw-18.03-lec25-16apr2003-220k.mp4"}
