{
  "title":"Lecture 17: Finding Particular Solutions via Fourier Series",
  "description": "",
  "file": null,
  "learning_resource_types": ["Lecture Videos"],
  "resource_type": "Video",
  "file_type": null,
  "youtube_key":  "yD0_EQLxHcw",
  "captions_file": "/courses/18-03-differential-equations-spring-2010/c1e97a3141e758569f1b1cd374404c56_yD0_EQLxHcw.vtt",
  "transcript_file": "/courses/18-03-differential-equations-spring-2010/57839a89c4d503a9768c85394bf46a11_yD0_EQLxHcw.pdf",
  "thumbnail_file": "https://img.youtube.com/vi/yD0_EQLxHcw/default.jpg",
  "archive_url": "http://www.archive.org/download/MIT18.03S06/mit-ocw-18.03-lec17-19mar2003-220k.mp4"}
